{
    "dialogues": [
        {
            "baseDialogue": {
                "character": "Man",
                "speakerSprite": [
                    "ManNeutral"
                ],
                "dialogue": "Beer! Beer! Beer!",
                "textSpeed": 0
            }
        },
        {
            "baseDialogue": {
                "character": "Girl",
                "speakerSprite": [
                    "GirlHappy"
                ],
                "dialogue": "Dad...",
                "textSpeed": 0
            }
        },
        {
            "baseDialogue": {
                "character": "Girl",
                "speakerSprite": [
                    "GirlHappy"
                ],
                "dialogue": "You're chanting for yourself.",
                "textSpeed": 0
            }
        },
        {
            "baseDialogue": {
                "character": "Man",
                "speakerSprite": [
                    "ManNeutral"
                ],
                "dialogue": "So what?",
                "textSpeed": 0
            }
        },
        {
            "baseDialogue": {
                "character": "Man",
                "speakerSprite": [
                    "ManNeutral"
                ],
                "dialogue": "We need to celebrate my recovery, hahaha!!",
                "textSpeed": 0
            }
        },
        {
            "baseDialogue": {
                "character": "Girl",
                "speakerSprite": [
                    "GirlHappy"
                ],
                "dialogue": "But I'm not even old enough to drink!",
                "textSpeed": 0
            }
        },
        {
            "baseDialogue": {
                "character": "Man",
                "speakerSprite": [
                    "ManNeutral"
                ],
                "dialogue": "It'll be aaaaaaaaaaaaalright! *hiccup*",
                "textSpeed": 0
            }
        },
        {
            "baseDialogue": {
                "character": "Man",
                "speakerSprite": [
                    "ManNeutral"
                ],
                "dialogue": "*retches very loudly*",
                "textSpeed": 0
            }
        },
        {
            "baseDialogue": {
                "character": "Girl",
                "speakerSprite": [
                    "GirlHappy"
                ],
                "dialogue": "Please, dad!",
                "textSpeed": 0
            }
        },
        {
            "baseDialogue": {
                "character": "Girl",
                "speakerSprite": [
                    "GirlHappy"
                ],
                "dialogue": "Come on, let's go home already!",
                "textSpeed": 0
            }
        },
        {
            "baseDialogue": {
                "character": "Lilith",
                "speakerSprite": [
                    "LilithFrown"
                ],
                "dialogue": "Your daughter's right, mister.",
                "textSpeed": 0
            }
        },
        {
            "baseDialogue": {
                "character": "Lilith",
                "speakerSprite": [
                    "LilithFrown"
                ],
                "dialogue": "You should really go home and get some rest.",
                "textSpeed": 0
            }
        },
        {
            "baseDialogue": {
                "character": "Lilith",
                "speakerSprite": [
                    "LilithFrown"
                ],
                "dialogue": "Why are you even still here?",
                "textSpeed": 0
            }
        },
        {
            "baseDialogue": {
                "character": "Man",
                "speakerSprite": [
                    "ManNeutral"
                ],
                "dialogue": "*hiccup* *hiccup*",
                "textSpeed": 0
            }
        },
        {
            "baseDialogue": {
                "character": "Man",
                "speakerSprite": [
                    "ManNeutral"
                ],
                "dialogue": "What are you two taaaaaaaaaaalking about?!",
                "textSpeed": 0
            }
        },
        {
            "baseDialogue": {
                "character": "Man",
                "speakerSprite": [
                    "ManNeutral"
                ],
                "dialogue": "The night's still young, haaaaaahaaaaaa!",
                "textSpeed": 0
            }
        },
        {
            "baseDialogue": {
                "character": "Man",
                "speakerSprite": [
                    "ManNeutral"
                ],
                "dialogue": "*vomits*",
                "textSpeed": 0
            }
        },
        {
            "baseDialogue": {
                "character": "Girl",
                "speakerSprite": [
                    "GirlHappy"
                ],
                "dialogue": "Dad, please!!",
                "textSpeed": 0
            },
            "endOfScene": true
        }
    ]
}