{
    "dialogues": [
        {
            "baseDialogue": {
                "character": "Man",
                "speakerSprite": [
                    "ManNeutral"
                ],
                "dialogue": "Hang in there, dear!",
                "textSpeed": 0
            }
        },
        {
            "baseDialogue": {
                "character": "Man",
                "speakerSprite": [
                    "ManNeutral"
                ],
                "dialogue": "Lilith, thank goodness you're here!",
                "textSpeed": 0
            }
        },
        {
            "baseDialogue": {
                "character": "Man",
                "speakerSprite": [
                    "ManNeutral"
                ],
                "dialogue": "Please help!!",
                "textSpeed": 0
            }
        },
        {
            "baseDialogue": {
                "character": "Man",
                "speakerSprite": [
                    "ManNeutral"
                ],
                "dialogue": "Hurry!!",
                "textSpeed": 0
            },
            "endOfScene": true
        }
    ]
}